Metadata-Version: 2.1
Name: kuran
Version: 0.1.0
Summary: A simple library for parsing and analyzing the Quran in Turkish.
Home-page: https://github.com/cobanov/kuran
Author: Mert Cobanov
Author-email: mertcobanov@gmail.com
License: MIT
Classifier: License :: OSI Approved :: MIT License
Classifier: Programming Language :: Python :: 3.9
Requires-Python: >=3.9
